<?xml version="1.0" encoding="utf-8" ?>
<problem
        package="ru.ejudge.sample_contest"
        id="A"
        type="standard">
  <statement language="ru_RU">
    <title>Условие</title>
    <description><p>Найдите корень(ни) уравнения x^4+ax^3+bx^2+cx+d=0 на отрезке [e,f] с точностью до третьего знака после запятой.</p>
</description>
    <input_format><p>Шесть, разделённых пробелами, вещественных чисел – a,b,c,d,e,f</p>
</input_format>
    <output_format><p>Корни уравнения разделённые пробелом с точностью 3 знака после запятой в порядке возрастания.</p>
</output_format>
    <notes><p>Если корни совпадают, вывести только один раз.</p>
</notes>
  </statement>
  <examples>
    <example>
      <input>-8 22 -24 9 0 2
</input>
      <output>1
</output>
    </example>
  </examples>
</problem>
